tiler_swift/1202121000.tif
tiler_swift/__init__.py
tiler_swift/py.typed
tiler_swift/quadkey.py
tiler_swift/scripts/__init__.py
tiler_swift/scripts/__main__.py
tiler_swift/scripts/quadkey.py
tiler_swift-1.1.0.dist-info/entry_points.txt
tiler_swift-1.1.0.dist-info/LICENSE.md
tiler_swift-1.1.0.dist-info/WHEEL
tiler_swift-1.1.0.dist-info/METADATA
tiler_swift-1.1.0.dist-info/RECORD
