Metadata-Version: 2.1
Name: tiler-swift
Version: 1.1.0
Summary: Tiler Swift, the swiftest quadkey tiler in the wild west
License: MIT
Author: Robofarm
Author-email: hello@robofarm.io
Requires-Python: >=3.8,<4.0
Classifier: License :: OSI Approved :: MIT License
Classifier: Programming Language :: Python :: 3
Classifier: Programming Language :: Python :: 3.8
Classifier: Programming Language :: Python :: 3.9
Requires-Dist: mercantile (>=1.1.6,<2.0.0)
Requires-Dist: numpy (>=1.19.5,<2.0.0)
Requires-Dist: rasterio (>=1.1.8,<2.0.0)
